.coveragerc
.git_archival.txt
.gitattributes
.gitignore
.readthedocs.yml
CHANGES.rst
LICENSE.rst
README.rst
pyproject.toml
requirements.txt
setup.cfg
setup.py
.github/workflows/linting.yml
.github/workflows/readthedocs.yml
.github/workflows/tests.yml
.github/workflows/tests_cron.yml
data/throughputs/lsst/README.rst
data/throughputs/lsst/total_g.dat
data/throughputs/lsst/total_i.dat
data/throughputs/lsst/total_r.dat
data/throughputs/lsst/total_u.dat
data/throughputs/lsst/total_y.dat
data/throughputs/lsst/total_z.dat
docs/Makefile
docs/make.bat
docs/source/citation.rst
docs/source/conf.py
docs/source/demo_roman_rubin_2023_photometry.ipynb
docs/source/demo_roman_rubin_2023_seds_singlemet.ipynb
docs/source/demos.rst
docs/source/index.rst
docs/source/installation.rst
docs/source/reference.rst
docs/source/rtd_environment.yaml
lsstdesc_diffsky/AlphaQ_z2ts.pkl
lsstdesc_diffsky/__init__.py
lsstdesc_diffsky/_version.py
lsstdesc_diffsky/constants.py
lsstdesc_diffsky/defaults.py
lsstdesc_diffsky/infer_diffcode_versions.py
lsstdesc_diffsky/pecZ.py
lsstdesc_diffsky/photometry_interpolation.py
lsstdesc_diffsky/write_mock_to_disk.py
lsstdesc_diffsky/write_mock_to_disk_singlemet.py
lsstdesc_diffsky.egg-info/PKG-INFO
lsstdesc_diffsky.egg-info/SOURCES.txt
lsstdesc_diffsky.egg-info/dependency_links.txt
lsstdesc_diffsky.egg-info/requires.txt
lsstdesc_diffsky.egg-info/top_level.txt
lsstdesc_diffsky/black_hole_modeling/__init__.py
lsstdesc_diffsky/black_hole_modeling/black_hole_accretion_rate.py
lsstdesc_diffsky/black_hole_modeling/black_hole_mass.py
lsstdesc_diffsky/config_files/diffsky_v0.1.0_pscan_3765.yaml
lsstdesc_diffsky/config_files/diffsky_v0.1.0_pscan_39991.yaml
lsstdesc_diffsky/config_files/diffsky_v0.1.1_pscan_3765.yaml
lsstdesc_diffsky/config_files/diffsky_v0.1.1_pscan_39991.yaml
lsstdesc_diffsky/config_files/diffsky_v0.2.0_roman_rubin.yaml
lsstdesc_diffsky/config_files/diffsky_v0.2.1_roman_rubin.yaml
lsstdesc_diffsky/config_files/roman_rubin_2023_v0.1.0.yaml
lsstdesc_diffsky/config_files/roman_rubin_2023_v0.1.1.yaml
lsstdesc_diffsky/config_files/roman_rubin_2023_v0.2.0.yaml
lsstdesc_diffsky/config_files/roman_rubin_2023_v0.2.1.yaml
