Metadata-Version: 2.1
Name: lsstdesc-diffsky
Version: 1.1.1
Summary: Library for differentiable generation of synthetic skies for LSST DESC
Author-email: Andrew Hearin <ahearin@anl.gov>, Eve Kovacs <kovacs@anl.gov>
License: BSD 3-Clause License
Project-URL: home, https://github.com/ArgonneCPAC/lsstdesc_diffsky
Classifier: Programming Language :: Python :: 3
Requires-Python: >=3.9
License-File: LICENSE.rst
Requires-Dist: numpy
Requires-Dist: jax
Requires-Dist: numba
Requires-Dist: mpi4py
Requires-Dist: scipy
Requires-Dist: h5py
Requires-Dist: astropy
Requires-Dist: healpy
Requires-Dist: halotools
Requires-Dist: galsampler
Requires-Dist: psutil
Requires-Dist: diffmah
Requires-Dist: diffstar
Requires-Dist: dsps
Requires-Dist: galsim
